{"filter":false,"title":"ethereum.json","tooltip":"/ethereum.json","undoManager":{"mark":0,"position":-1,"stack":[[{"start":{"row":15,"column":7},"end":{"row":15,"column":49},"action":"remove","lines":["0xdedb49385ad5b94a16f236a6890cf9e0b1e30392"],"id":29},{"start":{"row":15,"column":7},"end":{"row":15,"column":49},"action":"insert","lines":["0x1cd57aaa814859b3073ddc1b30b0eddd8ac2fdff"]}]]},"ace":{"folds":[],"scrolltop":119,"scrollleft":0,"selection":{"start":{"row":15,"column":7},"end":{"row":15,"column":49},"isBackwards":false},"options":{"guessTabSize":true,"useWrapMode":false,"wrapToView":true},"firstLineState":{"row":5,"state":"start","mode":"ace/mode/json"}},"timestamp":1449289242867,"hash":"eb7a60edcb541757f4704d6f7d904c1aab36c1ee"}